{
  "scope": "india_multi_city",
  "cities": [
    "agra",
    "ahmedabad",
    "amritsar",
    "bengaluru",
    "bhagalpur",
    "bhavnagar",
    "bhopal",
    "bhubaneswar",
    "chandigarh",
    "chennai",
    "coimbatore",
    "darbhanga",
    "dehradun",
    "delhi",
    "faridabad",
    "gaya",
    "goa",
    "greater-noida",
    "gurgaon",
    "guwahati",
    "gwalior",
    "hyderabad",
    "indore",
    "jaipur",
    "jammu",
    "jamshedpur",
    "kanpur",
    "kochi",
    "kolkata",
    "lucknow",
    "ludhiana",
    "meerut",
    "mumbai",
    "muzaffarpur",
    "mysuru",
    "nagpur",
    "nashik",
    "new-delhi",
    "noida",
    "patna",
    "pune",
    "raipur",
    "rajkot",
    "ranchi",
    "shimla",
    "srinagar",
    "surat",
    "thiruvananthapuram",
    "vadodara",
    "vaishali",
    "varanasi",
    "visakhapatnam"
  ],
  "n_zones": 208817,
  "test_accuracy": 0.7812685240071132,
  "cv_f1_macro": 0.7855666820616152,
  "cv_f1_std": 0.004741753578351343,
  "classification_report": {
    "low": {
      "precision": 0.9114036504603457,
      "recall": 0.8885826771653543,
      "f1-score": 0.8998484969300694,
      "support": 12700.0
    },
    "moderate": {
      "precision": 0.7960942614008292,
      "recall": 0.7855528043922919,
      "f1-score": 0.7907884042264969,
      "support": 18578.0
    },
    "high": {
      "precision": 0.6591083781706379,
      "recall": 0.6688767550702028,
      "f1-score": 0.6639566395663956,
      "support": 12820.0
    },
    "critical": {
      "precision": 0.7469963839962673,
      "recall": 0.7810708623002806,
      "f1-score": 0.7636537085618889,
      "support": 8199.0
    },
    "accuracy": 0.7812685240071132,
    "macro avg": {
      "precision": 0.77840066850702,
      "recall": 0.7810207747320325,
      "f1-score": 0.7795618123212127,
      "support": 52297.0
    },
    "weighted avg": {
      "precision": 0.7828184849930965,
      "recall": 0.7812685240071132,
      "f1-score": 0.7819275247236335,
      "support": 52297.0
    }
  },
  "brier_per_class": {
    "low": 0.03458800614069666,
    "moderate": 0.10688218485253521,
    "high": 0.11198535481040538,
    "critical": 0.05426424905931332
  },
  "features": [
    "ndvi",
    "ndbi",
    "builtup_density",
    "impervious_fraction",
    "water_dist_m",
    "latitude",
    "longitude"
  ]
}